pyworldzipcode/AD.zcsv
pyworldzipcode/AR.zcsv
pyworldzipcode/AS.zcsv
pyworldzipcode/AT.zcsv
pyworldzipcode/AU.zcsv
pyworldzipcode/AX.zcsv
pyworldzipcode/AZ.zcsv
pyworldzipcode/BD.zcsv
pyworldzipcode/BE.zcsv
pyworldzipcode/BG.zcsv
pyworldzipcode/BM.zcsv
pyworldzipcode/BR.zcsv
pyworldzipcode/BY.zcsv
pyworldzipcode/CA.zcsv
pyworldzipcode/CH.zcsv
pyworldzipcode/CL.zcsv
pyworldzipcode/CO.zcsv
pyworldzipcode/CR.zcsv
pyworldzipcode/CY.zcsv
pyworldzipcode/CZ.zcsv
pyworldzipcode/DE.zcsv
pyworldzipcode/DK.zcsv
pyworldzipcode/DO.zcsv
pyworldzipcode/DZ.zcsv
pyworldzipcode/EE.zcsv
pyworldzipcode/ES.zcsv
pyworldzipcode/FI.zcsv
pyworldzipcode/FM.zcsv
pyworldzipcode/FO.zcsv
pyworldzipcode/FR.zcsv
pyworldzipcode/GB.zcsv
pyworldzipcode/GF.zcsv
pyworldzipcode/GG.zcsv
pyworldzipcode/GL.zcsv
pyworldzipcode/GP.zcsv
pyworldzipcode/GT.zcsv
pyworldzipcode/GU.zcsv
pyworldzipcode/HR.zcsv
pyworldzipcode/HU.zcsv
pyworldzipcode/IE.zcsv
pyworldzipcode/IM.zcsv
pyworldzipcode/IN.zcsv
pyworldzipcode/IS.zcsv
pyworldzipcode/IT.zcsv
pyworldzipcode/JE.zcsv
pyworldzipcode/JP.zcsv
pyworldzipcode/KR.zcsv
pyworldzipcode/LI.zcsv
pyworldzipcode/LK.zcsv
pyworldzipcode/LT.zcsv
pyworldzipcode/LU.zcsv
pyworldzipcode/LV.zcsv
pyworldzipcode/MC.zcsv
pyworldzipcode/MD.zcsv
pyworldzipcode/MH.zcsv
pyworldzipcode/MK.zcsv
pyworldzipcode/MP.zcsv
pyworldzipcode/MQ.zcsv
pyworldzipcode/MT.zcsv
pyworldzipcode/MW.zcsv
pyworldzipcode/MX.zcsv
pyworldzipcode/MY.zcsv
pyworldzipcode/NC.zcsv
pyworldzipcode/NL.zcsv
pyworldzipcode/NO.zcsv
pyworldzipcode/NZ.zcsv
pyworldzipcode/PE.zcsv
pyworldzipcode/PH.zcsv
pyworldzipcode/PK.zcsv
pyworldzipcode/PL.zcsv
pyworldzipcode/PM.zcsv
pyworldzipcode/PR.zcsv
pyworldzipcode/PT.zcsv
pyworldzipcode/PW.zcsv
pyworldzipcode/RE.zcsv
pyworldzipcode/RO.zcsv
pyworldzipcode/RS.zcsv
pyworldzipcode/RU.zcsv
pyworldzipcode/SE.zcsv
pyworldzipcode/SG.zcsv
pyworldzipcode/SI.zcsv
pyworldzipcode/SJ.zcsv
pyworldzipcode/SK.zcsv
pyworldzipcode/SM.zcsv
pyworldzipcode/TH.zcsv
pyworldzipcode/TR.zcsv
pyworldzipcode-0.2.3.dist-info/LICENSE.txt
pyworldzipcode-0.2.3.dist-info/METADATA
pyworldzipcode-0.2.3.dist-info/WHEEL
pyworldzipcode-0.2.3.dist-info/entry_points.txt
pyworldzipcode-0.2.3.dist-info/top_level.txt
pyworldzipcode-0.2.3.dist-info/RECORD
