Metadata-Version: 2.1
Name: pyworldzipcode
Version: 0.2.3
Summary: infer geo location name using postal code
Home-page: https://github.com/dalwindr/worldpostalcode.git
Download-URL: https://github.com/dalwindr/worldpostalcode.git/tarball/0.1.0
Author: Dalwinder singh
Author-email: dalwindr@gmail.com
License: MIT
Keywords: api,geo-location,zipcode,devtools,Development,ziptastic,latitude,longitude
Classifier: Intended Audience :: Developers
Classifier: Topic :: Software Development :: Build Tools
Classifier: License :: OSI Approved :: MIT License
Classifier: Programming Language :: Python :: 2.7
Classifier: Programming Language :: Python :: 3
Classifier: Programming Language :: Python :: 3.4
License-File: LICENSE.txt
Requires-Dist: pandas (>=1.4)
